barnum/convert_data.py
barnum/source-data.pkl
barnum/gencc.py
barnum/gen_data.py
barnum/__init__.py
barnum/source-data/zip-codes.txt
barnum/source-data/male-prefix.txt
barnum/source-data/female-prefix.txt
barnum/source-data/email-domains.txt
barnum/source-data/area-codes.txt
barnum/source-data/company-types.txt
barnum/source-data/job-titles.txt
barnum/source-data/nounlist.txt
barnum/source-data/latin-words.txt
barnum/source-data/street-names.txt
barnum/source-data/female-first-name.txt
barnum/source-data/male-first-name.txt
barnum/source-data/company-names.txt
barnum/source-data/street-types.txt
barnum/source-data/last-name.txt
barnum-0.3.dist-info/DESCRIPTION.rst
barnum-0.3.dist-info/RECORD
barnum-0.3.dist-info/WHEEL
barnum-0.3.dist-info/top_level.txt
barnum-0.3.dist-info/metadata.json
barnum-0.3.dist-info/METADATA
