Metadata-Version: 2.0
Name: barnum
Version: 0.3
Summary: Create random data for your applications
Home-page: https://github.com/chris1610/barnum-proj
Author: Chris Moffitt
Author-email: chris@moffitts.net
License: GPL
Keywords: data
Platform: UNKNOWN
Classifier: Development Status :: 4 - Beta
Classifier: Intended Audience :: Developers
Classifier: Topic :: Software Development :: Build Tools
Classifier: License :: OSI Approved :: GNU General Public License (GPL)
Classifier: Programming Language :: Python :: 2.7
Classifier: Programming Language :: Python :: 3
Classifier: Programming Language :: Python :: 3.2
Classifier: Programming Language :: Python :: 3.3
Classifier: Programming Language :: Python :: 3.4
